Workbook

Sheet Catalogo
A1: ID | B1: Fonte | C1: Instituição | D1: Dimensão | E1: Cobertura (países) | F1: Última atualização | G1: Periodicidade | H1: Formato bruto | I1: Tem API/CSV aberto? | J1: Licença / uso | K1: Dificuldade de coleta | L1: Prioridade | M1: Indicadores-chave | N1: URL | O1: Observação
A2: GII-2025 | B2: Global Innovation Index 2025 | C2: WIPO | D2: META | E2: 133 economias | F2: 2025-09 | G2: Anual | H2: Tabela HTML (web publication) | I2: Sim (HTML) | J2: Aberto / atribuição | K2: Fácil | L2: Alta | M2: GII score; Sub-pillars: Institutions, Human capital, Infrastructure, Market, Business, Knowledge, Creative | N2: https://www.wipo.int/web-publications/global-innovation-index-2025/en/gii-2025-results.html | O2: Coletar via pandas.read_html da página de results — sem PDF parsing. URL confirmada pelo usuário.
A3: IEF-2026 | B3: Index of Economic Freedom 2026 | C3: Heritage Foundation | D3: META + MACRO | E3: 184 países | F3: 2026-03 | G3: Anual | H3: Tabela HTML (all-country-scores) | I3: Sim (HTML) | J3: Aberto / atribuição | K3: Fácil | L3: Alta | M3: Overall score; Rule of Law, Government Size, Regulatory Efficiency, Open Markets | N3: https://economicfreedom.heritage.org/pages/all-country-scores | O3: Coletar via pandas.read_html / scraping leve da página de scores — sem PDF. URL confirmada pelo usuário. Viés ideológico (libertário): tratar como UMA fonte, não verdade.
A4: HDI-2025 | B4: Human Development Index 2025 | C4: UNDP | D4: META | E4: 193 países | F4: 2025-05 | G4: Anual | H4: Excel + CSV abertos | I4: Sim (CSV oficial) | J4: CC BY | K4: Fácil | L4: Alta | M4: HDI; Life expectancy, Education, GNI per capita PPP | N4: https://hdr.undp.org/data-center | O4: Padrão-ouro pra desenvolvimento humano. Cobertura quase universal.
A5: WHR-2025 | B5: World Happiness Report 2025 | C5: Wellbeing Research Centre / Oxford | D5: META | E5: ~140 países | F5: 2025-03 | G5: Anual | H5: Excel/CSV | I5: Sim | J5: CC BY | K5: Fácil | L5: Média | M5: Cantril ladder; GDP, Social support, Healthy life, Freedom, Generosity, Corruption | N5: https://worldhappiness.report/data-sharing/ | O5: Boa pra cruzar com qualidade de vida subjetiva.
A6: BLI | B6: OECD Better Life Index | C6: OECD | D6: META | E6: 41 países (OECD + parceiros) | F6: 2024-11 | G6: Anual | H6: CSV via OECD.Stat | I6: Sim (API) | J6: OECD terms | K6: Fácil | L6: Média | M6: 11 dimensões: housing, income, jobs, community, education, environment, civic, health, life satisfaction, safety, work-life balance | N6: https://www.oecdbetterlifeindex.org/ | O6: Cobre só países OECD — limita ranking global mas é rico onde cobre.
A7: SO-DEV-2024 | B7: Stack Overflow Developer Survey 2024 | C7: Stack Overflow | D7: TECH | E7: ~180 países (long tail rala) | F7: 2024-07 | G7: Anual | H7: CSV público | I7: Sim (CSV) | J7: ODbL | K7: Médio | L7: Alta | M7: Salário mediano por país (USD); tech stack popularity; remote-work share | N7: https://survey.stackoverflow.co/ | O7: N por país varia muito. Filtrar por país com N >= 100 antes de ranquear.
A8: GTCI-2023 | B8: Global Talent Competitiveness Index | C8: INSEAD / Portulans | D8: TECH + VISA | E8: 134 países | F8: 2023-11 | G8: Bienal/Anual (atrasado) | H8: PDF + Excel | I8: Sim (Excel oficial) | J8: Aberto / atribuição | K8: Fácil | L8: Alta | M8: GTCI score; Enable, Attract, Grow, Retain, Vocational/technical skills, Global Knowledge skills | N8: https://www.insead.edu/global-indices/gtci | O8: Ed. 2024 atrasada — usar 2023 enquanto isso.
A9: IMD-WTR-2025 | B9: World Talent Ranking 2025 | C9: IMD Business School | D9: TECH + VISA | E9: 67 economias | F9: 2025-09 | G9: Anual | H9: PDF + Excel para assinantes | I9: Não (paywall pra dataset completo, ranking público) | J9: Comercial | K9: Difícil | L9: Média | M9: Investment & development, Appeal, Readiness | N9: https://www.imd.org/centers/wcc/world-competitiveness-center/rankings/world-talent-ranking/ | O9: Ranking aberto é suficiente. Pular se for caro extrair.
A10: LEVELS-FYI | B10: Levels.fyi compensation data | C10: Levels.fyi | D10: TECH | E10: ~30 países com dado denso | F10: Contínuo (live) | G10: Contínuo | H10: Site (sem API oficial) | I10: Não (scraping ou export manual) | J10: ToS restritivo | K10: Difícil | L10: Média | M10: Mediana de TC por nível (P3-P6) por país/cidade, foco em big tech | N10: https://www.levels.fyi/ | O10: Melhor dado de compensação real, mas legal/ético pra scrapar é cinza. Considerar export manual da página por país.
A11: GCI-2024 | B11: Global Cybersecurity Index 2024 | C11: ITU | D11: TECH + MACRO | E11: 194 países | F11: 2024-09 | G11: Bienal | H11: PDF + Excel | I11: Sim | J11: CC BY | K11: Fácil | L11: Baixa | M11: GCI overall; Legal, Technical, Organisational, Capacity, Cooperation | N11: https://www.itu.int/epublications/publication/global-cybersecurity-index-2024/ | O11: Útil só se você prioriza segurança de SI. Senão, pular.
A12: HENLEY-2026 | B12: Henley Passport Index 2026 | C12: Henley & Partners | D12: VISA | E12: 199 passaportes | F12: 2026-01 | G12: Trimestral | H12: Tabela web + PDF | I12: Não (sem CSV oficial) | J12: Comercial / atribuição | K12: Médio | L12: Alta | M12: Visa-free/visa-on-arrival score do passaporte BR e dos destinos | N12: https://www.henleyglobal.com/passport-index | O12: Importante pra calcular ganho de mobilidade pós-naturalização (BR vs. DE, PT, etc.).
... A34: TIMEZONE-CALC | B34: Diferença de fuso para US East/West | C34: Cálculo geográfico | D34: TECH (modo remoto) | E34: 190 países | F34: Estático | G34: — | H34: Calculado | I34: Sim | J34: N/A | K34: Fácil | L34: Média | M34: tz_offset_us_east, tz_offset_us_west, hours_overlap_business | N34: — | O34: Pra modo remoto com cliente US, overlap de 4h+ é requisito de quase toda vaga.

Sheet Resumo
A1: Dimensão | B1: Total fontes | C1: Alta prioridade | D1: Média prioridade | E1: Baixa prioridade | F1: Fáceis de coletar
A2: META — Índice composto multi-dimensional | B2: =COUNTIF(Catalogo!D2:D34,"*META*") -> 7 | C2: =COUNTIFS(Catalogo!D2:D34,"*META*",Catalogo!L2:L34,"Alta") -> 3 | D2: =COUNTIFS(Catalogo!D2:D34,"*META*",Catalogo!L2:L34,"Média") -> 3 | E2: =COUNTIFS(Catalogo!D2:D34,"*META*",Catalogo!L2:L34,"Baixa") -> 1 | F2: =COUNTIFS(Catalogo!D2:D34,"*META*",Catalogo!K2:K34,"Fácil") -> 5
A3: TECH — Mercado de trabalho tech / salário | B3: =COUNTIF(Catalogo!D2:D34,"*TECH*") -> 8 | C3: =COUNTIFS(Catalogo!D2:D34,"*TECH*",Catalogo!L2:L34,"Alta") -> 2 | D3: =COUNTIFS(Catalogo!D2:D34,"*TECH*",Catalogo!L2:L34,"Média") -> 5 | E3: =COUNTIFS(Catalogo!D2:D34,"*TECH*",Catalogo!L2:L34,"Baixa") -> 1 | F3: =COUNTIFS(Catalogo!D2:D34,"*TECH*",Catalogo!K2:K34,"Fácil") -> 4
A4: VISA — Facilidade de visto / pathway | B4: =COUNTIF(Catalogo!D2:D34,"*VISA*") -> 9 | C4: =COUNTIFS(Catalogo!D2:D34,"*VISA*",Catalogo!L2:L34,"Alta") -> 6 | D4: =COUNTIFS(Catalogo!D2:D34,"*VISA*",Catalogo!L2:L34,"Média") -> 3 | E4: =COUNTIFS(Catalogo!D2:D34,"*VISA*",Catalogo!L2:L34,"Baixa") -> 0 | F4: =COUNTIFS(Catalogo!D2:D34,"*VISA*",Catalogo!K2:K34,"Fácil") -> 2
A5: PPP — Custo de vida / salário líquido em PPP | B5: =COUNTIF(Catalogo!D2:D34,"*PPP*") -> 9 | C5: =COUNTIFS(Catalogo!D2:D34,"*PPP*",Catalogo!L2:L34,"Alta") -> 5 | D5: =COUNTIFS(Catalogo!D2:D34,"*PPP*",Catalogo!L2:L34,"Média") -> 3 | E5: =COUNTIFS(Catalogo!D2:D34,"*PPP*",Catalogo!L2:L34,"Baixa") -> 1 | F5: =COUNTIFS(Catalogo!D2:D34,"*PPP*",Catalogo!K2:K34,"Fácil") -> 3
A6: MACRO — Estabilidade macro e segurança | B6: =COUNTIF(Catalogo!D2:D34,"*MACRO*") -> 10 | C6: =COUNTIFS(Catalogo!D2:D34,"*MACRO*",Catalogo!L2:L34,"Alta") -> 6 | D6: =COUNTIFS(Catalogo!D2:D34,"*MACRO*",Catalogo!L2:L34,"Média") -> 2 | E6: =COUNTIFS(Catalogo!D2:D34,"*MACRO*",Catalogo!L2:L34,"Baixa") -> 2 | F6: =COUNTIFS(Catalogo!D2:D34,"*MACRO*",Catalogo!K2:K34,"Fácil") -> 8
A7: TOTAL (linhas únicas) | B7: =COUNTA(Catalogo!A2:A34) -> 33 | C7: =COUNTIF(Catalogo!L2:L34,"Alta") -> 17 | D7: =COUNTIF(Catalogo!L2:L34,"Média") -> 12 | E7: =COUNTIF(Catalogo!L2:L34,"Baixa") -> 4 | F7: =COUNTIF(Catalogo!K2:K34,"Fácil") -> 17

Sheet Legenda
A1: Coluna | B1: Como ler
A2: Dimensão | B2: META=composto, TECH=mercado tech, VISA=imigração, PPP=custo de vida & impostos, MACRO=estabilidade & segurança
A3: Cobertura | B3: Quantos países o dataset cobre. <100 limita ranking global.
A4: Formato bruto | B4: Como o dado é publicado originalmente.
A5: Tem API/CSV aberto? | B5: Sim = extração programática trivial. Não = parsing/scraping/manual.
A6: Licença / uso | B6: CC BY = uso livre com atribuição. Comercial = pode haver restrição. ODbL = ok pra derivar.
A7: Dificuldade de coleta | B7: Fácil = baixar 1 arquivo; Médio = parsing PDF / múltiplas páginas; Difícil = scraping ou paywall.
A8: Prioridade | B8: Alta = entra no MVP; Média = V2; Baixa = só se sobrar tempo.
A10: Próximo passo | B10: Validar este catálogo com o Guilherme antes de qualquer extração de dados.
